mwa_hyperbeam-0.10.4.dist-info/METADATA
mwa_hyperbeam-0.10.4.dist-info/WHEEL
mwa_hyperbeam-0.10.4.dist-info/licenses/COPYING-hdf5
mwa_hyperbeam-0.10.4.dist-info/licenses/LICENSE
mwa_hyperbeam-0.10.4.dist-info/licenses/LICENSE-erfa
mwa_hyperbeam/__init__.py
mwa_hyperbeam/mwa_hyperbeam.cpython-310-darwin.so
mwa_hyperbeam-0.10.4.dist-info/RECORD
