Metadata-Version: 2.4
Name: mwa_hyperbeam
Version: 0.10.4
Requires-Dist: numpy
License-File: LICENSE
License-File: LICENSE-erfa
License-File: COPYING-hdf5
Home-Page: https://github.com/MWATelescope/mwa_hyperbeam
Requires-Python: >=3.7
